{
    "ArtNo": "324173",
    "Attributs": [],
    "BrandName": "Belton",
    "BrandNo": "10049",
    "Documents": [],
    "GTIN": [
        "4015962838369"
    ],
    "GenArts": [
        {
            "Description": "RAL8014 BRUN SEPIA 400ML",
            "StandardisedArticleDescription": "RAL8014 BRUN SEPIA 400ML",
            "GenArtNo": -10049
        }
    ],
    "HasPartList": false,
    "HasTextInfo": false,
    "LogoBrand": [],
    "Pictures": [],
    "Replaced_by": [],
    "Replaces": [],
    "Status": "",
    "TradeNo": [],
    "URL": []
}