{
    "ArtNo": 684064,
    "Attributs": [],
    "BrandName": "GAMME SPRAY MAX 250ML",
    "BrandNo": "10049",
    "Documents": [],
    "GTIN": [
        "4015962855618"
    ],
    "GenArts": [
        {
            "Description": "SP VERNIS 2K RAPIDE 250ML",
            "StandardisedArticleDescription": "SP VERNIS 2K RAPIDE 250ML",
            "GenArtNo": -10049
        }
    ],
    "HasPartList": false,
    "HasTextInfo": false,
    "LogoBrand": [],
    "Pictures": [],
    "Replaced_by": [],
    "Replaces": [],
    "Status": "",
    "TradeNo": [],
    "URL": []
}