{
    "ArtNo": "DAKIT011",
    "Attributs": [],
    "BrandName": "Pneumatis",
    "BrandNo": "10026",
    "Documents": [],
    "GTIN": [
        "3666966020017"
    ],
    "GenArts": [
        {
            "Description": "Kit |Kit de fixation pour DP36318/0103 ",
            "StandardisedArticleDescription": "Kit |Kit de fixation pour DP36318/0103 ",
            "GenArtNo": -10026
        }
    ],
    "HasPartList": false,
    "HasTextInfo": false,
    "LogoBrand": [
        {
            "Name": "PNEUMATIS.jpg",
            "Extension": "JPG",
            "Path": "/img/10026/PNEUMATIS.jpg"
        }
    ],
    "Pictures": [],
    "Replaced_by": [],
    "Replaces": [],
    "Status": "",
    "TradeNo": [
        "DAKIT011"
    ],
    "URL": []
}