{"ArtNo":"250200 (12V) / 250290 (24V)","BrandNo":"10002","BrandName":"VIGNAL","LogoBrand":[{"Name":"VIGNAL","Extension":"VIGNAL","Path":"/img/10002/VIGNAL"}],"GenArts": [{"GenartNo":-1000,"StandardisedArticleDescription":"","AssemblyGroup":"","PurposeOfUse":"","Description":"INTER"}],"Attributs": [{"Attribute":"Secteur","Value":"","SortNo":1},{"Attribute":"Caractéristiques","Value":"Largeur : 30 mm, Consommation : 180W, Tension : 12 ou 24V, Profondeur : 63 mm, Longueur   : 30 mm, Fonctions Principales : Commutateur rotatif 2 positions : Marche / Arrêt, permet d actionner un triangle, un gyrophare, une barre équipée, ...,","SortNo":2}]}