{"ArtNo":"280069","BrandNo":"10002","BrandName":"VIGNAL","LogoBrand":[{"Name":"VIGNAL","Extension":"VIGNAL","Path":"/img/10002/VIGNAL"}],"GenArts": [{"GenartNo":-1000,"StandardisedArticleDescription":"","AssemblyGroup":"","PurposeOfUse":"","Description":"FCA"}],"Attributs": [{"Attribute":"Secteur","Value":"Camions et Poids lourds, Remorques et Semi-remorques, Utilitaires, Agricole, Minier, Manutention et Chariots élévateurs, Construction et Engins de chantier, Forestier","SortNo":1},{"Attribute":"Caractéristiques","Value":"ADR : ADR, Terminaison 1 : JPT 2 voies femelle, Terminaison 2 : JPT 2 voies mâle, Type de Produit : Faisceau feux latéraux,","SortNo":2}]}