{"ArtNo":"D14681","BrandNo":"10002","BrandName":"VIGNAL","LogoBrand":[{"Name":"VIGNAL","Extension":"VIGNAL","Path":"/img/10002/VIGNAL"}],"GenArts": [{"GenartNo":-1000,"StandardisedArticleDescription":"","AssemblyGroup":"","PurposeOfUse":"","Description":"Accessoires systèmes filaires"}],"Attributs": [{"Attribute":"Secteur","Value":"Camions et Poids lourds, Remorques et Semi-remorques, Utilitaires, Agricole, Minier, Manutention et Chariots élévateurs, Construction et Engins de chantier, Forestier","SortNo":1},{"Attribute":"Caractéristiques","Value":"Consommation : 10W, Couleur : Oui, Type de Produit : Filaire HD 720P/1080P, Tension : 12/24 V, Résistance aux Vibrations : ISO 16750-3 - max 6,3G, Taille Ecran : 10\", Dimensions Ecran : 267mm (L) x 159,5mm (l) x 30mm (p), Résolution : 1024 x 3 (RGB) x 600, Audio : Haut parleur intégré, Langues : Français, Anglais, Chinois, Allemand, Japonais, Espagnol, Italien, Russe, Néerlandais, Mode Affichage : normal, horizontal, vertical, miroir, Max Caméras : 4 caméras max, Pare-Soleil : Oui, Standard Vidéo : PAL / NTSC/FLIP/FLIP-MIRROR, Affichage écran : Mono, Ecran tactile : Oui,","SortNo":2}]}