{"ArtNo":"D16004","BrandNo":"10002","BrandName":"VIGNAL","LogoBrand":[{"Name":"VIGNAL","Extension":"VIGNAL","Path":"/img/10002/VIGNAL"}],"GenArts": [{"GenartNo":-1000,"StandardisedArticleDescription":"","AssemblyGroup":"","PurposeOfUse":"","Description":"SESA Pulsar"}],"Attributs": [{"Attribute":"Secteur","Value":"Camions et Poids lourds, Remorques et Semi-remorques, Utilitaires, Construction et Engins de chantier","SortNo":1},{"Attribute":"Caractéristiques","Value":"Connecteur : Cables fils nus, Couleur : Ambre / Orange, Fixation : A visser, Protection IP : IP69K, Largeur : 38 mm, Matière Cabochon : Polycarbonate, Nombre de LED : 4, Source : LED, Tension : 12/24 V, Garantie : 2 ans, Longueur   : 94 mm, Ampérage : 0,45 AMP à 12V, Profondeur : 22 mm, Modes de Flash : 7 modes de flash, ECE : R65 classe 1, CEM : ECE R10-06,","SortNo":2}]}