{"ArtNo":"WL42603","BrandNo":"10002","BrandName":"Wynn's","LogoBrand":[{"Name":"mylogo","Extension":"png","Path":"/img/10002/mylogo.png"}],"GenArts": [{"GenartNo":-1000,"StandardisedArticleDescription":"","AssemblyGroup":"","PurposeOfUse":"","Description":"Scratch Remover - 150ml"}],"Attributs": [{"Attribute":"Référence mentionnée sur flacon","Value":"PN42603","SortNo":1},{"Attribute":"Dénomination produit","Value":"Scratch Remover - 150ml","SortNo":2},{"Attribute":"Sous titre produit","Value":"Efface rayure","SortNo":3},{"Attribute":"Caractéristiques","Value":"Élimine les rayures légères, les éraflures, les frottements et les décolorations. Sans danger pour toutes les finitions de peinture.","SortNo":4}],"Pictures":[{"Name":"my_pictures","Extension":"jpg","SortNo":1,"Path":"/img/10002/my_pictures.jpg"}]}