{"ArtNo":"25033","BrandNo":"10004","BrandName":"LURO","LogoBrand":[{"Name":"LURO","Extension":"LURO","Path":"/img/10004/LURO"}],"GenArts": [{"GenartNo":-1000,"StandardisedArticleDescription":"","AssemblyGroup":"","PurposeOfUse":"","Description":"PULVÉRISATEUR PNEUMATIQUE ACIER 30 L"}],"Attributs": [{"Attribute":"Caractéristiques","Value":"Le pulvérisateur 30 litres en acier mobile autonome est approprié aux produits de pH neutre (valeur 7). Une fois l'appareil mis sous pression (6 bar) il devient indépendant de toute source d'énergie. Il est livré avec un entonnoir de remplissage et est muni d'une jauge latérale. Une lance standard est livrée de série. Il est recommandé de rincer l'appareil après chaque utilisation.","SortNo":1},{"Attribute":"Fiche technique","Value":"https://www.calameo.com/read/0062998755f4e486a79d0","SortNo":2}]}