{
    "ArtNo": "1467LF/2",
    "Attributs": [
        {
            "Attribute": "Description",
            "Value": "Purgeur de freins électronique",
            "SortNo": 1
        }
    ],
    "BrandName": "Beta",
    "BrandNo": "10013",
    "Documents": [],
    "GTIN": [
        "8054809163321"
    ],
    "GenArts": [
        {
            "Description": "Purgeur de freins électronique",
            "StandardisedArticleDescription": "Purgeur de freins électronique",
            "GenArtNo": -10013
        }
    ],
    "HasPartList": false,
    "HasTextInfo": false,
    "LogoBrand": [
        {
            "Name": "16.jpg",
            "Extension": "JPG",
            "Path": "/img/10013/16.jpg"
        }
    ],
    "Pictures": [
        {
            "Name": "1467LF_slash_2.jpg",
            "Extension": "JPG",
            "Path": "/img/10013/1467LF_slash_2.jpg",
            "SortNo": 1
        }
    ],
    "Replaced_by": [],
    "Replaces": [],
    "Status": "",
    "TradeNo": [
        "014670099"
    ],
    "URL": []
}