{
    "ArtNo": "1688PC",
    "Attributs": [
        {
            "Attribute": "Description",
            "Value": "Pointe à tracer rétractable en carbure en acier trempé chromé",
            "SortNo": 1
        },
        {
            "Attribute": "L\nmm",
            "Value": "150",
            "SortNo": 2
        },
        {
            "Attribute": "Ø\nmm",
            "Value": "1",
            "SortNo": 3
        }
    ],
    "BrandName": "Beta",
    "BrandNo": "10013",
    "Documents": [],
    "GTIN": [
        "8014230801179"
    ],
    "GenArts": [
        {
            "Description": "Pointe à tracer rétractable en carbure en acier trempé chromé",
            "StandardisedArticleDescription": "Pointe à tracer rétractable en carbure en acier trempé chromé",
            "GenArtNo": -10013
        }
    ],
    "HasPartList": false,
    "HasTextInfo": false,
    "LogoBrand": [
        {
            "Name": "10.jpg",
            "Extension": "JPG",
            "Path": "/img/10013/10.jpg"
        }
    ],
    "Pictures": [
        {
            "Name": "1688PC.jpg",
            "Extension": "JPG",
            "Path": "/img/10013/1688PC.jpg",
            "SortNo": 1
        }
    ],
    "Replaced_by": [],
    "Replaces": [],
    "Status": "",
    "TradeNo": [
        "016880300"
    ],
    "URL": []
}