{
    "ArtNo": "1693M",
    "Attributs": [
        {
            "Attribute": "Description",
            "Value": "Appareil de mesure de distance laser multifonction, 80 m",
            "SortNo": 1
        },
        {
            "Attribute": "H\nmm",
            "Value": "115",
            "SortNo": 2
        },
        {
            "Attribute": "L\nmm",
            "Value": "48",
            "SortNo": 3
        },
        {
            "Attribute": "S\nmm",
            "Value": "29",
            "SortNo": 4
        }
    ],
    "BrandName": "Beta",
    "BrandNo": "10013",
    "Documents": [],
    "GTIN": [
        "8054809128283"
    ],
    "GenArts": [
        {
            "Description": "Appareil de mesure de distance laser multifonction, 80 m",
            "StandardisedArticleDescription": "Appareil de mesure de distance laser multifonction, 80 m",
            "GenArtNo": -10013
        }
    ],
    "HasPartList": false,
    "HasTextInfo": false,
    "LogoBrand": [
        {
            "Name": "10.jpg",
            "Extension": "JPG",
            "Path": "/img/10013/10.jpg"
        }
    ],
    "Pictures": [
        {
            "Name": "1693M.jpg",
            "Extension": "JPG",
            "Path": "/img/10013/1693M.jpg",
            "SortNo": 1
        }
    ],
    "Replaced_by": [],
    "Replaces": [],
    "Status": "",
    "TradeNo": [
        "016930080"
    ],
    "URL": []
}