{
    "ArtNo": "1750PF",
    "Attributs": [
        {
            "Attribute": "Description",
            "Value": "Cartouches de graisse universelles pour pompe à graisse 1750",
            "SortNo": 1
        },
        {
            "Attribute": "g",
            "Value": "550",
            "SortNo": 2
        }
    ],
    "BrandName": "Beta",
    "BrandNo": "10013",
    "Documents": [],
    "GTIN": [
        "8054809605746"
    ],
    "GenArts": [
        {
            "Description": "Cartouches de graisse universelles pour pompe à graisse 1750",
            "StandardisedArticleDescription": "Cartouches de graisse universelles pour pompe à graisse 1750",
            "GenArtNo": -10013
        }
    ],
    "HasPartList": false,
    "HasTextInfo": false,
    "LogoBrand": [
        {
            "Name": "11.jpg",
            "Extension": "JPG",
            "Path": "/img/10013/11.jpg"
        }
    ],
    "Pictures": [
        {
            "Name": "1750PF.jpg",
            "Extension": "JPG",
            "Path": "/img/10013/1750PF.jpg",
            "SortNo": 1
        }
    ],
    "Replaced_by": [],
    "Replaces": [],
    "Status": "",
    "TradeNo": [
        "017500161"
    ],
    "URL": []
}