{
    "ArtNo": "1778V18",
    "Attributs": [
        {
            "Attribute": "Description",
            "Value": "Couteau à cran d'arrêt en aluminium • avec etui",
            "SortNo": 1
        },
        {
            "Attribute": "L\nmm",
            "Value": "195",
            "SortNo": 2
        },
        {
            "Attribute": "A\nmm",
            "Value": "25",
            "SortNo": 3
        },
        {
            "Attribute": "L1\nmm",
            "Value": "85",
            "SortNo": 4
        }
    ],
    "BrandName": "Beta",
    "BrandNo": "10013",
    "Documents": [],
    "GTIN": [
        "8014230844022"
    ],
    "GenArts": [
        {
            "Description": "Couteau à cran d'arrêt en aluminium • avec etui",
            "StandardisedArticleDescription": "Couteau à cran d'arrêt en aluminium • avec etui",
            "GenArtNo": -10013
        }
    ],
    "HasPartList": false,
    "HasTextInfo": false,
    "LogoBrand": [
        {
            "Name": "11.jpg",
            "Extension": "JPG",
            "Path": "/img/10013/11.jpg"
        }
    ],
    "Pictures": [
        {
            "Name": "1778V18.jpg",
            "Extension": "JPG",
            "Path": "/img/10013/1778V18.jpg",
            "SortNo": 1
        }
    ],
    "Replaced_by": [],
    "Replaces": [],
    "Status": "",
    "TradeNo": [
        "017780018"
    ],
    "URL": []
}