{
    "ArtNo": "1827/K",
    "Attributs": [
        {
            "Attribute": "Description",
            "Value": "Fer à souder au gaz avec 7 accessoires en coffret avec plateau en mousse compacte",
            "SortNo": 1
        }
    ],
    "BrandName": "BetaWELDING",
    "BrandNo": "10013",
    "Documents": [],
    "GTIN": [
        "8014230513676"
    ],
    "GenArts": [
        {
            "Description": "Fer à souder au gaz avec 7 accessoires en coffret avec plateau en mousse compacte",
            "StandardisedArticleDescription": "Fer à souder au gaz avec 7 accessoires en coffret avec plateau en mousse compacte",
            "GenArtNo": -10013
        }
    ],
    "HasPartList": false,
    "HasTextInfo": false,
    "LogoBrand": [
        {
            "Name": "28.jpg",
            "Extension": "JPG",
            "Path": "/img/10013/28.jpg"
        }
    ],
    "Pictures": [
        {
            "Name": "1827_slash_K.jpg",
            "Extension": "JPG",
            "Path": "/img/10013/1827_slash_K.jpg",
            "SortNo": 1
        }
    ],
    "Replaced_by": [],
    "Replaces": [],
    "Status": "",
    "TradeNo": [
        "018270100"
    ],
    "URL": []
}