{
    "ArtNo": "1934MAV70",
    "Attributs": [
        {
            "Attribute": "Description",
            "Value": "Micro-meuleuse droite à grande vitesse",
            "SortNo": 1
        },
        {
            "Attribute": "g",
            "Value": "210",
            "SortNo": 2
        }
    ],
    "BrandName": "Beta",
    "BrandNo": "10013",
    "Documents": [],
    "GTIN": [
        "8014230728827"
    ],
    "GenArts": [
        {
            "Description": "Micro-meuleuse droite à grande vitesse",
            "StandardisedArticleDescription": "Micro-meuleuse droite à grande vitesse",
            "GenArtNo": -10013
        }
    ],
    "HasPartList": false,
    "HasTextInfo": false,
    "LogoBrand": [
        {
            "Name": "17.jpg",
            "Extension": "JPG",
            "Path": "/img/10013/17.jpg"
        }
    ],
    "Pictures": [
        {
            "Name": "1934MAV70.jpg",
            "Extension": "JPG",
            "Path": "/img/10013/1934MAV70.jpg",
            "SortNo": 1
        }
    ],
    "Replaced_by": [],
    "Replaces": [],
    "Status": "",
    "TradeNo": [
        "019340030"
    ],
    "URL": []
}