{
    "ArtNo": "1938R/L",
    "Attributs": [
        {
            "Attribute": "Description",
            "Value": "Lames pour couteau vibrant dépose-vitres",
            "SortNo": 1
        },
        {
            "Attribute": "L \nmm",
            "Value": "36",
            "SortNo": 2
        }
    ],
    "BrandName": "Beta",
    "BrandNo": "10013",
    "Documents": [],
    "GTIN": [
        "8014230702926"
    ],
    "GenArts": [
        {
            "Description": "Lames pour couteau vibrant dépose-vitres",
            "StandardisedArticleDescription": "Lames pour couteau vibrant dépose-vitres",
            "GenArtNo": -10013
        }
    ],
    "HasPartList": false,
    "HasTextInfo": false,
    "LogoBrand": [
        {
            "Name": "17.jpg",
            "Extension": "JPG",
            "Path": "/img/10013/17.jpg"
        }
    ],
    "Pictures": [
        {
            "Name": "1938R_slash_L.jpg",
            "Extension": "JPG",
            "Path": "/img/10013/1938R_slash_L.jpg",
            "SortNo": 1
        }
    ],
    "Replaced_by": [],
    "Replaces": [],
    "Status": "",
    "TradeNo": [
        "019380045"
    ],
    "URL": []
}