{
    "ArtNo": "310/C8",
    "Attributs": [
        {
            "Attribute": "Description",
            "Value": "Fer à souder avec composition de 7 matrices",
            "SortNo": 1
        }
    ],
    "BrandName": "Beta",
    "BrandNo": "10013",
    "Documents": [],
    "GTIN": [
        "8014230159737"
    ],
    "GenArts": [
        {
            "Description": "Fer à souder avec composition de 7 matrices",
            "StandardisedArticleDescription": "Fer à souder avec composition de 7 matrices",
            "GenArtNo": -10013
        }
    ],
    "HasPartList": false,
    "HasTextInfo": false,
    "LogoBrand": [
        {
            "Name": "13.jpg",
            "Extension": "JPG",
            "Path": "/img/10013/13.jpg"
        }
    ],
    "Pictures": [
        {
            "Name": "310_slash_C8.jpg",
            "Extension": "JPG",
            "Path": "/img/10013/310_slash_C8.jpg",
            "SortNo": 1
        }
    ],
    "Replaced_by": [],
    "Replaces": [],
    "Status": "",
    "TradeNo": [
        "003100108"
    ],
    "URL": []
}