{
    "ArtNo": "31SE",
    "Attributs": [
        {
            "Attribute": "Description",
            "Value": "Chasse-goupilles pour goupilles élastiques",
            "SortNo": 1
        },
        {
            "Attribute": "Ø \nmm",
            "Value": "6",
            "SortNo": 2
        },
        {
            "Attribute": "D \nmm",
            "Value": "3,6",
            "SortNo": 3
        },
        {
            "Attribute": "L \nmm",
            "Value": "175",
            "SortNo": 4
        },
        {
            "Attribute": "L1 \nmm",
            "Value": "80",
            "SortNo": 5
        },
        {
            "Attribute": "S \nmm",
            "Value": "12",
            "SortNo": 6
        }
    ],
    "BrandName": "Beta",
    "BrandNo": "10013",
    "Documents": [],
    "GTIN": [
        "8014230075778"
    ],
    "GenArts": [
        {
            "Description": "Chasse-goupilles pour goupilles élastiques",
            "StandardisedArticleDescription": "Chasse-goupilles pour goupilles élastiques",
            "GenArtNo": -10013
        }
    ],
    "HasPartList": false,
    "HasTextInfo": false,
    "LogoBrand": [
        {
            "Name": "07.jpg",
            "Extension": "JPG",
            "Path": "/img/10013/07.jpg"
        }
    ],
    "Pictures": [
        {
            "Name": "31SE.jpg",
            "Extension": "JPG",
            "Path": "/img/10013/31SE.jpg",
            "SortNo": 1
        }
    ],
    "Replaced_by": [],
    "Replaces": [],
    "Status": "",
    "TradeNo": [
        "000310206"
    ],
    "URL": []
}