{
    "ArtNo": "3932U",
    "Attributs": [
        {
            "Attribute": "Description",
            "Value": "Dérive-chaîne professionnel compatible avec chaînes de 5 à 11 vitesses",
            "SortNo": 1
        },
        {
            "Attribute": "L\nmm",
            "Value": "164",
            "SortNo": 2
        },
        {
            "Attribute": "L1\nmm",
            "Value": "115",
            "SortNo": 3
        }
    ],
    "BrandName": "Beta",
    "BrandNo": "10013",
    "Documents": [],
    "GTIN": [
        "8014230882482"
    ],
    "GenArts": [
        {
            "Description": "Dérive-chaîne professionnel compatible avec chaînes de 5 à 11 vitesses",
            "StandardisedArticleDescription": "Dérive-chaîne professionnel compatible avec chaînes de 5 à 11 vitesses",
            "GenArtNo": -10013
        }
    ],
    "HasPartList": false,
    "HasTextInfo": false,
    "LogoBrand": [
        {
            "Name": "16_bici.jpg",
            "Extension": "JPG",
            "Path": "/img/10013/16_bici.jpg"
        }
    ],
    "Pictures": [
        {
            "Name": "3932U.jpg",
            "Extension": "JPG",
            "Path": "/img/10013/3932U.jpg",
            "SortNo": 1
        }
    ],
    "Replaced_by": [],
    "Replaces": [],
    "Status": "",
    "TradeNo": [
        "039320011"
    ],
    "URL": []
}