{
    "ArtNo": "720S",
    "Attributs": [
        {
            "Attribute": "Description",
            "Value": "Douille à chocs pour vis 6 pans creux, carré femelle 1/2\", série compacte, phosphatée",
            "SortNo": 1
        },
        {
            "Attribute": " \nmm",
            "Value": "24",
            "SortNo": 2
        },
        {
            "Attribute": "Ø \nmm",
            "Value": "33,8",
            "SortNo": 3
        },
        {
            "Attribute": "L \nmm",
            "Value": "28,0",
            "SortNo": 4
        },
        {
            "Attribute": "Ø1 \nmm",
            "Value": "30,0",
            "SortNo": 5
        },
        {
            "Attribute": "A \nmm",
            "Value": "10,5",
            "SortNo": 6
        }
    ],
    "BrandName": "Beta",
    "BrandNo": "10013",
    "Documents": [],
    "GTIN": [
        "8014230823966"
    ],
    "GenArts": [
        {
            "Description": "Douille à chocs pour vis 6 pans creux, carré femelle 1/2\", série compacte, phosphatée",
            "StandardisedArticleDescription": "Douille à chocs pour vis 6 pans creux, carré femelle 1/2\", série compacte, phosphatée",
            "GenArtNo": -10013
        }
    ],
    "HasPartList": false,
    "HasTextInfo": false,
    "LogoBrand": [
        {
            "Name": "03.jpg",
            "Extension": "JPG",
            "Path": "/img/10013/03.jpg"
        }
    ],
    "Pictures": [
        {
            "Name": "720S.jpg",
            "Extension": "JPG",
            "Path": "/img/10013/720S.jpg",
            "SortNo": 1
        }
    ],
    "Replaced_by": [],
    "Replaces": [],
    "Status": "",
    "TradeNo": [
        "007200124"
    ],
    "URL": []
}