{
    "ArtNo": "7552N",
    "Attributs": [
        {
            "Attribute": "Description",
            "Value": "Polo de travail noir en coton piqué 200 g/m2",
            "SortNo": 1
        },
        {
            "Attribute": "",
            "Value": "XXXL",
            "SortNo": 2
        }
    ],
    "BrandName": "Beta",
    "BrandNo": "10013",
    "Documents": [],
    "GTIN": [
        "8054809637334"
    ],
    "GenArts": [
        {
            "Description": "Polo de travail noir en coton piqué 200 g/m2",
            "StandardisedArticleDescription": "Polo de travail noir en coton piqué 200 g/m2",
            "GenArtNo": -10013
        }
    ],
    "HasPartList": false,
    "HasTextInfo": false,
    "LogoBrand": [
        {
            "Name": "21ww.jpg",
            "Extension": "JPG",
            "Path": "/img/10013/21ww.jpg"
        }
    ],
    "Pictures": [
        {
            "Name": "7552N.jpg",
            "Extension": "JPG",
            "Path": "/img/10013/7552N.jpg",
            "SortNo": 1
        }
    ],
    "Replaced_by": [],
    "Replaces": [],
    "Status": "",
    "TradeNo": [
        "075520406"
    ],
    "URL": []
}