{
    "ArtNo": "867RIBE/L",
    "Attributs": [
        {
            "Attribute": "Description",
            "Value": "Embout pour visseuses pour vis RIBE®",
            "SortNo": 1
        },
        {
            "Attribute": "",
            "Value": "M13",
            "SortNo": 2
        },
        {
            "Attribute": "L\nmm",
            "Value": "75",
            "SortNo": 3
        }
    ],
    "BrandName": "Beta",
    "BrandNo": "10013",
    "Documents": [],
    "GTIN": [
        "8014230844015"
    ],
    "GenArts": [
        {
            "Description": "Embout pour visseuses pour vis RIBE®",
            "StandardisedArticleDescription": "Embout pour visseuses pour vis RIBE®",
            "GenArtNo": -10013
        }
    ],
    "HasPartList": false,
    "HasTextInfo": false,
    "LogoBrand": [
        {
            "Name": "05.jpg",
            "Extension": "JPG",
            "Path": "/img/10013/05.jpg"
        }
    ],
    "Pictures": [
        {
            "Name": "867RIBE_slash_L.jpg",
            "Extension": "JPG",
            "Path": "/img/10013/867RIBE_slash_L.jpg",
            "SortNo": 1
        }
    ],
    "Replaced_by": [],
    "Replaces": [],
    "Status": "",
    "TradeNo": [
        "008670763"
    ],
    "URL": []
}