{
    "ArtNo": "920.../C12...",
    "Attributs": [
        {
            "Attribute": "Description",
            "Value": "Plateau thermoformé vide",
            "SortNo": 1
        }
    ],
    "BrandName": "Beta",
    "BrandNo": "10013",
    "Documents": [],
    "GTIN": [
        "8014230079882"
    ],
    "GenArts": [
        {
            "Description": "Plateau thermoformé vide",
            "StandardisedArticleDescription": "Plateau thermoformé vide",
            "GenArtNo": -10013
        }
    ],
    "HasPartList": false,
    "HasTextInfo": false,
    "LogoBrand": [
        {
            "Name": "03.jpg",
            "Extension": "JPG",
            "Path": "/img/10013/03.jpg"
        }
    ],
    "Pictures": [
        {
            "Name": "920A_slash_C12X_2.jpg",
            "Extension": "JPG",
            "Path": "/img/10013/920A_slash_C12X_2.jpg",
            "SortNo": 1
        }
    ],
    "Replaced_by": [],
    "Replaces": [],
    "Status": "",
    "TradeNo": [
        "098990116"
    ],
    "URL": []
}