{
    "ArtNo": "953",
    "Attributs": [
        {
            "Attribute": "Description",
            "Value": "Clé mâle 6 pans à béquille à cardan",
            "SortNo": 1
        },
        {
            "Attribute": "mm",
            "Value": "10",
            "SortNo": 2
        },
        {
            "Attribute": "L \nmm",
            "Value": "440",
            "SortNo": 3
        },
        {
            "Attribute": "L1 \nmm",
            "Value": "200",
            "SortNo": 4
        },
        {
            "Attribute": "Ø \nmm",
            "Value": "22",
            "SortNo": 5
        },
        {
            "Attribute": "H \nmm",
            "Value": "13",
            "SortNo": 6
        }
    ],
    "BrandName": "Beta",
    "BrandNo": "10013",
    "Documents": [],
    "GTIN": [
        "8014230038834"
    ],
    "GenArts": [
        {
            "Description": "Clé mâle 6 pans à béquille à cardan",
            "StandardisedArticleDescription": "Clé mâle 6 pans à béquille à cardan",
            "GenArtNo": -10013
        }
    ],
    "HasPartList": false,
    "HasTextInfo": false,
    "LogoBrand": [
        {
            "Name": "05.jpg",
            "Extension": "JPG",
            "Path": "/img/10013/05.jpg"
        }
    ],
    "Pictures": [
        {
            "Name": "953.jpg",
            "Extension": "JPG",
            "Path": "/img/10013/953.jpg",
            "SortNo": 1
        }
    ],
    "Replaced_by": [],
    "Replaces": [],
    "Status": "",
    "TradeNo": [
        "009530200"
    ],
    "URL": []
}