{
    "ArtNo": "9589B/36",
    "Attributs": [
        {
            "Attribute": "Description",
            "Value": "Paquet de 36 rouleaux de ruban adhésif pour emballage, logo Beta, blanc",
            "SortNo": 1
        }
    ],
    "BrandName": "BETACollection",
    "BrandNo": "10013",
    "Documents": [],
    "GTIN": [
        "8014230542317"
    ],
    "GenArts": [
        {
            "Description": "Paquet de 36 rouleaux de ruban adhésif pour emballage, logo Beta, blanc",
            "StandardisedArticleDescription": "Paquet de 36 rouleaux de ruban adhésif pour emballage, logo Beta, blanc",
            "GenArtNo": -10013
        }
    ],
    "HasPartList": false,
    "HasTextInfo": false,
    "LogoBrand": [
        {
            "Name": "91.jpg",
            "Extension": "JPG",
            "Path": "/img/10013/91.jpg"
        }
    ],
    "Pictures": [
        {
            "Name": "9589B_slash_36.jpg",
            "Extension": "JPG",
            "Path": "/img/10013/9589B_slash_36.jpg",
            "SortNo": 1
        }
    ],
    "Replaced_by": [],
    "Replaces": [],
    "Status": "",
    "TradeNo": [
        "095890036"
    ],
    "URL": []
}