{
    "ArtNo": "960AVE",
    "Attributs": [
        {
            "Attribute": "Description",
            "Value": "Outil pour le contrôle des injecteurs électroniques Diesel Common Rail",
            "SortNo": 1
        }
    ],
    "BrandName": "Beta",
    "BrandNo": "10013",
    "Documents": [],
    "GTIN": [
        "8014230627106"
    ],
    "GenArts": [
        {
            "Description": "Outil pour le contrôle des injecteurs électroniques Diesel Common Rail",
            "StandardisedArticleDescription": "Outil pour le contrôle des injecteurs électroniques Diesel Common Rail",
            "GenArtNo": -10013
        }
    ],
    "HasPartList": false,
    "HasTextInfo": false,
    "LogoBrand": [
        {
            "Name": "16.jpg",
            "Extension": "JPG",
            "Path": "/img/10013/16.jpg"
        }
    ],
    "Pictures": [
        {
            "Name": "960AVE.jpg",
            "Extension": "JPG",
            "Path": "/img/10013/960AVE.jpg",
            "SortNo": 1
        }
    ],
    "Replaced_by": [],
    "Replaces": [],
    "Status": "",
    "TradeNo": [
        "009600245"
    ],
    "URL": []
}