{
    "ArtNo": "96TBP/S",
    "Attributs": [
        {
            "Attribute": "Description",
            "Value": "Jeu de clés mâles 6 pans coudées à tête sphérique et à poignée en T chromées",
            "SortNo": 1
        }
    ],
    "BrandName": "Beta",
    "BrandNo": "10013",
    "Documents": [],
    "GTIN": [
        "8014230697925"
    ],
    "GenArts": [
        {
            "Description": "Jeu de clés mâles 6 pans coudées à tête sphérique et à poignée en T chromées",
            "StandardisedArticleDescription": "Jeu de clés mâles 6 pans coudées à tête sphérique et à poignée en T chromées",
            "GenArtNo": -10013
        }
    ],
    "HasPartList": false,
    "HasTextInfo": false,
    "LogoBrand": [
        {
            "Name": "05.jpg",
            "Extension": "JPG",
            "Path": "/img/10013/05.jpg"
        }
    ],
    "Pictures": [
        {
            "Name": "96TBP_slash_S6.jpg",
            "Extension": "JPG",
            "Path": "/img/10013/96TBP_slash_S6.jpg",
            "SortNo": 1
        }
    ],
    "Replaced_by": [],
    "Replaces": [],
    "Status": "",
    "TradeNo": [
        "000960694"
    ],
    "URL": []
}