{
    "ArtNo": "C30M",
    "Attributs": [
        {
            "Attribute": "Description",
            "Value": "Établi mobile MaxiTank",
            "SortNo": 1
        }
    ],
    "BrandName": "Beta",
    "BrandNo": "10013",
    "Documents": [],
    "GTIN": [
        "8054809229300"
    ],
    "GenArts": [
        {
            "Description": "Établi mobile MaxiTank",
            "StandardisedArticleDescription": "Établi mobile MaxiTank",
            "GenArtNo": -10013
        }
    ],
    "HasPartList": false,
    "HasTextInfo": false,
    "LogoBrand": [
        {
            "Name": "01.jpg",
            "Extension": "JPG",
            "Path": "/img/10013/01.jpg"
        }
    ],
    "Pictures": [
        {
            "Name": "C30M.jpg",
            "Extension": "JPG",
            "Path": "/img/10013/C30M.jpg",
            "SortNo": 1
        }
    ],
    "Replaced_by": [],
    "Replaces": [],
    "Status": "",
    "TradeNo": [
        "030000300"
    ],
    "URL": []
}