{
    "ArtNo": "324194",
    "Attributs": [],
    "BrandName": "AUTO K",
    "BrandNo": "10049",
    "Documents": [],
    "GTIN": [
        "4015962838543"
    ],
    "GenArts": [
        {
            "Description": "RAL9018 BLANC PAPYR.400ML",
            "StandardisedArticleDescription": "RAL9018 BLANC PAPYR.400ML",
            "GenArtNo": -10049
        }
    ],
    "HasPartList": false,
    "HasTextInfo": false,
    "LogoBrand": [],
    "Pictures": [],
    "Replaced_by": [],
    "Replaces": [],
    "Status": "",
    "TradeNo": [],
    "URL": []
}