{
    "ArtNo": "680149",
    "Attributs": [],
    "BrandName": "AUTO K",
    "BrandNo": "10049",
    "Documents": [],
    "GTIN": [
        "4015962854161"
    ],
    "GenArts": [
        {
            "Description": "SM PIERRE A FUSIL 205139",
            "StandardisedArticleDescription": "SM PIERRE A FUSIL 205139",
            "GenArtNo": -10049
        }
    ],
    "HasPartList": false,
    "HasTextInfo": false,
    "LogoBrand": [
        {
            "Name": "AUTOK.jpg",
            "Extension": "JPG",
            "Path": "10049/AUTOK.jpg"
        }
    ],
    "Pictures": [],
    "Replaced_by": [],
    "Replaces": [],
    "Status": "",
    "TradeNo": [],
    "URL": []
}