{
    "ArtNo": 680139,
    "Attributs": [],
    "BrandName": "AUTO K",
    "BrandNo": "10049",
    "Documents": [],
    "GTIN": [
        "4015962853805"
    ],
    "GenArts": [
        {
            "Description": "SM GRIS 612 PLASTIQUE",
            "StandardisedArticleDescription": "SM GRIS 612 PLASTIQUE",
            "GenArtNo": -10049
        }
    ],
    "HasPartList": false,
    "HasTextInfo": false,
    "LogoBrand": [],
    "Pictures": [],
    "Replaced_by": [],
    "Replaces": [],
    "Status": "",
    "TradeNo": [],
    "URL": []
}